{
    "base": {
        "task_choice": "Wall",
        "side_choice": "Border",
        "id": 67
    },
    "objects": [
        {
            "type": "Clock",
            "name": "MetalClock.usd",
            "file_path": "I/Clock/MetalClock.usd",
            "image_path": "I/Clock/.thumbs/256x256/MetalClock.usd.png",
            "prim_path": "/World/objects/Clock",
            "xform_name": "Clock",
            "transform": {
                "translation": [
                    -51.963340759277344,
                    -0.9151479601860046,
                    55.1329345703125
                ],
                "rotation": [
                    0.9999999963958383,
                    -5.2847961019068656e-05,
                    -6.91759885345788e-07,
                    -6.644499954891356e-05
                ],
                "scale": 1.0
            },
            "use_network": false,
            "action": [
                -0.5196340931152873,
                -0.4486701778856899
            ],
            "reward": {
                "affordance": 2.5071917479387067
            }
        },
        {
            "type": "Clock",
            "name": "OversizedClock.usd",
            "file_path": "I/Clock/OversizedClock.usd",
            "image_path": "I/Clock/.thumbs/256x256/OversizedClock.usd.png",
            "prim_path": "/World/objects/Clock_01",
            "xform_name": "Clock_01",
            "transform": {
                "translation": [
                    10.74166488647461,
                    -1.0047268867492676,
                    18.67060089111328
                ],
                "rotation": [
                    1,
                    0,
                    0,
                    0
                ],
                "scale": 1.0
            },
            "use_network": false,
            "action": [
                0.10744502701408667,
                -0.8141336531532988
            ],
            "reward": {
                "affordance": 2.553264212142064
            }
        },
        {
            "type": "Clock",
            "name": "OversizedClock.usd",
            "file_path": "I/Clock/OversizedClock.usd",
            "image_path": "I/Clock/.thumbs/256x256/OversizedClock.usd.png",
            "prim_path": "/World/objects/Clock_02",
            "xform_name": "Clock_02",
            "transform": {
                "translation": [
                    -39.85081100463867,
                    -1.000000238418579,
                    188.9417724609375
                ],
                "rotation": [
                    1,
                    0,
                    0,
                    0
                ],
                "scale": 1.0
            },
            "use_network": false,
            "action": [
                -0.39850811344791787,
                0.8894445192552444
            ],
            "reward": {
                "affordance": 1.512451171875
            }
        }
    ]
}