{
    "base": {
        "task_choice": "Wall",
        "side_choice": "Border",
        "id": 150
    },
    "objects": [
        {
            "type": "Picture",
            "name": "Painting_04.usd",
            "file_path": "I/Picture/Painting_04.usd",
            "image_path": "I/Picture/.thumbs/256x256/Painting_04.usd.png",
            "prim_path": "/World/objects/Picture",
            "xform_name": "Picture",
            "transform": {
                "translation": [
                    19.59528350830078,
                    -1.000504732131958,
                    10.361420631408691
                ],
                "rotation": [
                    1,
                    0,
                    0,
                    0
                ],
                "scale": 1.0
            },
            "use_network": false,
            "bounding_box": [
                [
                    -56.9877383335255,
                    -6.086331465616133,
                    -47.15846115044867
                ],
                [
                    96.17901373701383,
                    -0.9684230596367345,
                    73.21212527293581
                ]
            ],
            "action": [
                0.19595281633701983,
                -0.8980527908781805
            ],
            "reward": {
                "affordance": 2.500465341091774,
                "collision": 0.0
            }
        },
        {
            "type": "Clock",
            "name": "Industrial_Clock.usd",
            "file_path": "I/Clock/Industrial_Clock.usd",
            "image_path": "I/Clock/.thumbs/256x256/Industrial_Clock.usd.png",
            "prim_path": "/World/objects/Clock",
            "xform_name": "Clock",
            "transform": {
                "translation": [
                    -91.21734619140625,
                    -0.8979895710945129,
                    16.178661346435547
                ],
                "rotation": [
                    0.9999996423721313,
                    0.0003815840184997169,
                    -0.000753871745985937,
                    3.6423026188357344e-05
                ],
                "scale": 1.0
            },
            "use_network": false,
            "bounding_box": [
                [
                    -123.60908074554433,
                    -5.549993872116756,
                    -12.628377621755636
                ],
                [
                    -60.47795372952338,
                    13.184423908567764,
                    67.44798390045874
                ]
            ],
            "action": [
                -0.9119492149801944,
                -0.8394509059159705
            ],
            "reward": {
                "affordance": 3.707449392583933,
                "collision": 0.0
            }
        },
        {
            "type": "Picture",
            "name": "FramedPicture_Wide03.usd",
            "file_path": "I/Picture/FramedPicture_Wide03.usd",
            "image_path": "I/Picture/.thumbs/256x256/FramedPicture_Wide03.usd.png",
            "prim_path": "/World/objects/Picture_01",
            "xform_name": "Picture_01",
            "transform": {
                "translation": [
                    -84.32585144042969,
                    -1.0,
                    122.52506256103516
                ],
                "rotation": [
                    1,
                    0,
                    0,
                    0
                ],
                "scale": 1.0
            },
            "use_network": false,
            "bounding_box": [
                [
                    -133.7916522026025,
                    -0.999981533240209,
                    100.05645370483705
                ],
                [
                    -34.86004972457518,
                    2.1822008010955254,
                    144.99367184097142
                ]
            ],
            "action": [
                -0.8432585038552146,
                0.22525063578203944
            ],
            "reward": {
                "affordance": 0.0,
                "collision": 0.0
            }
        }
    ]
}